cmnLib/__init__.py
cmnLib/mem.py
cmnLib/pcie.py
cmnLib/saLibrary.py
cmnLib/security.py
cmnLib/text.py
cmnLib/tmpWorkAround.py
cmnLib-1.0.12.dist-info/METADATA
cmnLib-1.0.12.dist-info/WHEEL
cmnLib-1.0.12.dist-info/top_level.txt
cmnLib-1.0.12.dist-info/RECORD
