Metadata-Version: 2.1
Name: cmnLib
Version: 1.0.12
Summary: The cmnLib - is all of my personal python shell libraries for pypi later for dissection
Home-page: https://bitbucket.org/guengn/cmnLib/src
Author: Guyen Gankhuyag
Author-email: guyen800@protonmail.com
License: MIT
Platform: UNKNOWN
Requires-Dist: pexpect
Requires-Dist: pycrypto
